mts/__init__.py
mts/_msr.py
mts/_mt.py
mts/_rt.py
mts/_t.py
mts/py.typed
mt_system-2.0.3.dist-info/METADATA
mt_system-2.0.3.dist-info/WHEEL
mt_system-2.0.3.dist-info/licenses/LICENSE
mt_system-2.0.3.dist-info/RECORD
