Metadata-Version: 2.3
Name: mt-system
Version: 2.0.3
Summary: Python library of MT system.
Project-URL: Homepage, https://github.com/stfukuda/mt-system.git
Project-URL: Documentation, https://stfukuda.github.io/mt-system/
Project-URL: Source, https://github.com/stfukuda/mt-system.git
Project-URL: Issues, https://github.com/stfukuda/mt-system/issues
Author-email: Shota Fukuda <st_fukuda@outlook.jp>
License: 
Classifier: Development Status :: 5 - Production/Stable
Classifier: Intended Audience :: Developers
Classifier: Intended Audience :: Science/Research
Classifier: License :: OSI Approved :: BSD License
Classifier: Operating System :: MacOS
Classifier: Operating System :: Microsoft :: Windows
Classifier: Operating System :: POSIX
Classifier: Operating System :: Unix
Classifier: Programming Language :: Python :: 3
Classifier: Programming Language :: Python :: 3 :: Only
Classifier: Programming Language :: Python :: 3.9
Classifier: Programming Language :: Python :: 3.10
Classifier: Programming Language :: Python :: 3.11
Classifier: Programming Language :: Python :: 3.12
Classifier: Programming Language :: Python :: 3.13
Classifier: Topic :: Scientific/Engineering
Classifier: Topic :: Software Development
Requires-Python: >=3.9
Requires-Dist: scikit-learn>=1.4.0
